<?xml version="1.0"?>
<apiservice client="site">
  <name>Aesir - Content Webservice</name>
  <author/>
  <copyright/>
  <description/>
  <config>
    <name>content</name>
    <version>1.0.0</version>
    <authorizationAssetName>com_{webserviceName}</authorizationAssetName>
  </config>
  <operations>
    <documentation authorizationNeeded="false" source="auto" url=""/>
    <create authorizationNeeded="false" strictFields="false" authorization="" dataMode="helper" optionName="" modelClassName="" modelClassPath="" isAdminClass="false" functionName="save" functionArgs="" validateData="none" validateDataFunction="validate" tableName="">
      <resources>
        <resource displayName="result" fieldFormat="{result}" transform="string"/>
      </resources>
    </create>
  </operations>
  <complexArrays/>
</apiservice>
